AUTHORS.md
HISTORY.md
LICENSE
README.md
docs/developer.md
docs/history.md
docs/index.md
docs/installation.md
docs/usage.md
omicron/__init__.py
omicron/config/__init__.py
omicron/config/calendar.json
omicron/config/defaults.yaml
omicron/config/dev.yaml
omicron/config/schema.py
omicron/config/sql/v0.6.sql
omicron/config/sql/v1.0.sql
omicron/core/__init__.py
omicron/core/constants.py
omicron/core/errors.py
omicron/core/events.py
omicron/core/triggers.py
omicron/dal/__init__.py
omicron/dal/cache.py
omicron/dal/influx/__init__.py
omicron/dal/influx/errors.py
omicron/dal/influx/escape.py
omicron/dal/influx/flux.py
omicron/dal/influx/influxclient.py
omicron/dal/influx/serialize.py
omicron/extensions/__init__.py
omicron/extensions/decimals.py
omicron/extensions/np.py
omicron/models/__init__.py
omicron/models/board.py
omicron/models/security.py
omicron/models/stock.py
omicron/models/timeframe.py
omicron/notify/__init__.py
omicron/notify/dingtalk.py
omicron/notify/mail.py
omicron/notify/tts.py
omicron/plotting/__init__.py
omicron/plotting/candlestick.py
omicron/plotting/metrics.py
omicron/talib/__init__.py
omicron/talib/core.py
omicron/talib/morph.py
tests/__init__.py
tests/pyrightconfig.json
zillionare_omicron-2.0.0.dist-info/LICENSE
zillionare_omicron-2.0.0.dist-info/METADATA
zillionare_omicron-2.0.0.dist-info/WHEEL
zillionare_omicron-2.0.0.dist-info/RECORD
