Metadata-Version: 2.1
Name: zillionare-omicron
Version: 2.0.0
Summary: Core Library for Zillionare
Home-page: https://zillionare-omicron.readthedocs.io
License: MIT
Keywords: AI,quant,trade,stock
Author: jieyu
Author-email: code@jieyu.ai
Requires-Python: >=3.8,<3.9
Classifier: Development Status :: 3 - Alpha
Classifier: Intended Audience :: Developers
Classifier: License :: OSI Approved :: MIT License
Classifier: Natural Language :: English
Classifier: Programming Language :: Python :: 3
Classifier: Programming Language :: Python :: 3.8
Classifier: Programming Language :: Python :: 3.8
Provides-Extra: dev
Provides-Extra: doc
Provides-Extra: test
Requires-Dist: Bottleneck (>=1.3.4,<2.0.0)
Requires-Dist: TA-Lib (>=0.4.25,<0.5.0) ; sys_platform == "linux"
Requires-Dist: aiohttp (>=3.8.0,<4.0.0)
Requires-Dist: aioredis (>=2.0.1,<3.0.0)
Requires-Dist: aiosmtplib (>=1.1.6,<2.0.0)
Requires-Dist: arrow (>=1.2,<2.0)
Requires-Dist: black (>=22.3.0,<23.0.0) ; extra == "test"
Requires-Dist: cfg4py (>=0.9)
Requires-Dist: ciso8601 (>=2.2.0,<3.0.0)
Requires-Dist: ckwrap (>=0.1.10,<0.2.0)
Requires-Dist: deprecation (>=2.1.0,<3.0.0)
Requires-Dist: empyrical-reloaded (>=0.5.8,<0.6.0)
Requires-Dist: flake8 (==4.0.1) ; extra == "test"
Requires-Dist: flake8-docstrings (>=1.6.0,<2.0.0) ; extra == "test"
Requires-Dist: freezegun (>=1.2.1,<2.0.0) ; extra == "test"
Requires-Dist: httpx (>=0.23.0,<0.24.0)
Requires-Dist: isort (==5.10.1) ; extra == "test"
Requires-Dist: livereload (>=2.6.3,<3.0.0) ; extra == "doc"
Requires-Dist: mike (>=1.1.2,<2.0.0) ; extra == "doc"
Requires-Dist: mkdocs (>=1.3.0,<2.0.0) ; extra == "doc"
Requires-Dist: mkdocs-autorefs (>=0.3.1,<0.4.0) ; extra == "doc"
Requires-Dist: mkdocs-include-markdown-plugin (>=3.2.3,<4.0.0) ; extra == "doc"
Requires-Dist: mkdocs-material (>=8.1.11,<9.0.0) ; extra == "doc"
Requires-Dist: mkdocs-material-extensions (>=1.0.3,<2.0.0)
Requires-Dist: mkdocstrings (>=0.18.0,<0.19.0) ; extra == "doc"
Requires-Dist: numpy (>=1.22,<2.0)
Requires-Dist: pandas (>=1.3.5,<2.0.0)
Requires-Dist: pip (>=22.0.3,<23.0.0) ; extra == "dev"
Requires-Dist: plotly (>=5.10.0,<6.0.0)
Requires-Dist: pre-commit (>=2.17.0,<3.0.0) ; extra == "dev"
Requires-Dist: psutil (>=5.7.3,<6.0.0) ; extra == "test"
Requires-Dist: pyreadline (>=2.1,<3.0)
Requires-Dist: pytest (>=7.0.1,<8.0.0) ; extra == "test"
Requires-Dist: pytest-cov (>=3.0.0,<4.0.0) ; extra == "test"
Requires-Dist: retry (>=0.9.2,<0.10.0)
Requires-Dist: scikit-learn (>=1.0.2,<2.0.0)
Requires-Dist: sh (==1.14.1)
Requires-Dist: toml (>=0.10.2,<0.11.0) ; extra == "dev"
Requires-Dist: tox (>=3.24.5,<4.0.0) ; extra == "dev"
Requires-Dist: twine (>=3.8.0,<4.0.0) ; extra == "dev"
Requires-Dist: zigzag (>=0.3,<0.4)
Requires-Dist: zillionare-core-types (>=0.5.2,<0.6.0)
Project-URL: Documentation, https://zillionare-omicron.readthedocs.io
Project-URL: Repository, https://github.com/zillionare/omicron
